pyhold/__init__.py
pyhold/pyhold.py
pyhold/pyholdkeyvalue.py
pyhold/pyholdlinkedlist.py
pyhold-0.2.1.dist-info/licenses/LICENSE
pyhold-0.2.1.dist-info/METADATA
pyhold-0.2.1.dist-info/WHEEL
pyhold-0.2.1.dist-info/top_level.txt
pyhold-0.2.1.dist-info/RECORD
