Metadata-Version: 2.4
Name: pyhold
Version: 0.2.1
Summary: A lightweight, persistent data store with dictionary, key-value, and linked list support with GUI
Home-page: https://github.com/AnjanB3012/pyhold
Author: Anjan Bellamkonda
License-Expression: MIT
Project-URL: Homepage, https://github.com/AnjanB3012/pyhold
Keywords: persistent,storage,key-value,linked-list,gui,xml,data-store
Classifier: Development Status :: 4 - Beta
Classifier: Intended Audience :: Developers
Classifier: Programming Language :: Python :: 3
Classifier: Programming Language :: Python :: 3.7
Classifier: Programming Language :: Python :: 3.8
Classifier: Programming Language :: Python :: 3.9
Classifier: Programming Language :: Python :: 3.10
Classifier: Programming Language :: Python :: 3.11
Classifier: Programming Language :: Python :: 3.12
Classifier: Topic :: Database
Classifier: Topic :: Software Development :: Libraries :: Python Modules
Classifier: Topic :: System :: Archiving
Classifier: Operating System :: OS Independent
Requires-Python: >=3.7
License-File: LICENSE
Dynamic: home-page
Dynamic: license-file
Dynamic: requires-python
